{"windows_01.windows操作系统查看端口占用.md":"o8Skljyp","linux_常见命令.md":"hkmOkrHl","linux_docker_03.docker安装mysql.md":"US6gX5PT","java_spring_01.源码编译.md":"Fcdx1xJw","index.md":"XcGoYKWN","linux_docker_02.docker命令.md":"P9tvWHYs","workflow_git_03.github-page部署.md":"RU26OBL9","linux_corn_01.corn安装及使用.md":"Boc6uzQl","workflow_git_01.git基本操作.md":"Po7vOY00","workflow_git_04.修改提交信息.md":"D8ancTKO","workflow_git_02.git常见命令.md":"59t85zag","nav.md":"-hAIGn_S","java_base_01.基础知识.md":"8-fozvvz","linux_docker_04.docker安装redis.md":"bUs882dp","linux_docker_01.docker安装.md":"FPupDake"}
