{"java_01.java基础_08.修饰符.md":"CWADolpI","java_01.java基础_06.接口.md":"CxqGE4T9","java_01.java基础_12.list接口.md":"DceeUe2M","index.md":"DTp7badz","java_01.java基础_02.基础类型.md":"EwSP4FVm","java_01.java基础_08.final关键字.md":"BtZZRfNT","java_01.java基础_14.map集合.md":"BRso1mn8","java_01.java基础_09.包装类.md":"DgBVI6R2","java_01.java基础_15.异常处理机制.md":"2m2KI3Os","java_01.java基础_03.基本运算符.md":"Djg1XOhV","java_01.java基础_11.常见的数据结构.md":"CSHeFVJG","java_01.java基础_01.基础知识.md":"C0n1dFJq","java_01.java基础_05.类和对象.md":"5cCmml9W","java_01.java基础_07.封装_继承和多态.md":"Cj74oBPC","java_01.java基础_18.缓冲流、转换流、序列化流、打印流.md":"DQ1wytcq","java_01.java基础_19.jvm类加载器.md":"BPMpMMrB","java_02.多线程和高并发_02.线程基础.md":"tv65lrsX","java_02.多线程和高并发_05.volatile关键字.md":"Cu7T0vJa","java_02.多线程和高并发_10.juc锁-locksupport.md":"C3HWlPgE","java_02.多线程和高并发_09.juc锁-核心aqs.md":"36h7_hLy","java_02.多线程和高并发_11.juc锁-reentrantreadwritelock.md":"Bu5Ey5zu","java_02.多线程和高并发_12.juc集合-concurrenthashmap.md":"BE5C14Dw","java_02.多线程和高并发_13.juc集合-copyonwritearraylist.md":"B7izb7oy","java_02.多线程和高并发_14.juc集合-concurrentlinkedqueue.md":"CtxYIy2b","java_02.多线程和高并发_15.juc集合-blockingqueue.md":"BURLf4qH","java_02.多线程和高并发_16.juc线程池-futuretask.md":"CH5sdyfs","java_02.多线程和高并发_17.juc线程池-threadpoolexecutor.md":"C7ku288O","java_02.多线程和高并发_18.juc线程池-scheduledthreadpoolexecutor.md":"BQ9bpR2S","java_02.多线程和高并发_19.juc线程池-forkjoin框架.md":"BrvvSO-M","java_02.多线程和高并发_20.juc工具类-countdownlatch.md":"DEDBVQQM","java_02.多线程和高并发_21.juc工具类-cyclicbarrier.md":"pFu24cqX","java_01.java基础_06.抽象类.md":"B-vNhoMY","java_02.多线程和高并发_23.juc工具类-phaser.md":"DSqW-u4e","web_03.javascript_03.运算符_01.算术运算符.md":"CcHTWK0k","java_01.java基础_13.set集合.md":"BYzCKmMP","web_03.javascript_04.语法相关_01.数据类型转化.md":"DU6Oo2QZ","linux_02.docker_06.docker安装nacos.md":"C6jNaSr5","linux_02.docker_07.docker安装kafka.md":"C95ucn4g","vue_01.基础_03.v-bind增强.md":"BRJc2W5g","linux_02.docker_08.docker安装mongodb.md":"BseOk8Ql","java_01.java基础_16.多线程，线程间通信以及线程池.md":"DhV_QLDW","java_05.spring_01.源码编译.md":"svv92S9o","java_05.spring_02.源码概览.md":"wOayrHGf","java_02.多线程和高并发_25.java 并发-threadlocal.md":"BbqPzpCG","vue_01.基础_07.脚手架使用及目录介绍.md":"C_deaXAL","java_05.spring_30.beanfactory和factorybean.md":"jaIYYoRo","java_03.jdk集合源码_01.collection类关系图.md":"DO5iIn12","java_04.jvm_01.jvm相关知识体系详解.md":"CqBs3vVb","linux_02.docker_02.docker命令.md":"DZIgI-h5","linux_02.docker_05.docker安装minio.md":"Bl-VEW4t","java_02.多线程和高并发_01.理论基础.md":"KGRQA97Y","linux_常见命令.md":"8VQMXbdC","web_03.javascript_04.语法相关_04.console对象与控制台.md":"Dk_1Lrhm","web_03.javascript_05.常见对象操作_08.math对象.md":"DDZMZmmW","web_03.javascript_05.常见对象操作_02.属性描述对象.md":"BfXbSccO","java_02.多线程和高并发_04.synchronize关键字.md":"CSncvPOD","java_02.多线程和高并发_07.juc初解.md":"WbnYaZ_7","java_02.多线程和高并发_03.java中的锁.md":"DPpAW01v","web_03.javascript_05.常见对象操作_09.date对象.md":"DLLnBxPN","web_03.javascript_06.面向对象编程_04.object对象的相关方法.md":"v9YBk1Uy","linux_02.docker_09.docker安装rocketmq.md":"DPLl9gSq","vue_01.基础_01.mvvm模式.md":"CXUEDlxm","web_02.css_01.css理论知识.md":"Df_4BXZQ","vue_01.基础_04.v-model在元素中使用.md":"icQ3mkQO","web_03.javascript_02.数据类型_06.数组.md":"MCHSZcce","java_02.多线程和高并发_24.juc工具类-exchanger.md":"s_hnHIzh","web_01.html_02.html标签-字体标签和超链接.md":"CKI3m_a5","web_01.html_03.图片标签.md":"C6nigHEA","web_01.html_01.html标签-排序标签.md":"BR6nNrcz","java_01.java基础_17.字节流和字符流.md":"BfZmbUGY","web_03.javascript_02.数据类型_02.null_ undefined 和布尔值.md":"Z2wVgZ40","vue_01.基础_08.组件.md":"BkEO7nrh","java_01.java基础_04.流程控制语句.md":"C5FwO-wz","web_04.es6_09.运算符的扩展.md":"Tf3aAm66","web_04.es6_10.symbol.md":"P8hJ2ihQ","web_04.es6_07.数组的扩展.md":"CU8OTE0b","web_04.es6_11.set和map.md":"uX_3_J76","web_04.es6_12.proxy.md":"C5Jz652I","web_03.javascript_08.dom操作_01.概述.md":"vNuK-Wi5","workflow_01.git_01.git基本操作.md":"C1rtkzJc","java_01.java基础_20.反射.md":"MDTUgmE4","web_04.es6_16. generator函数以及异步应用.md":"BmJr0Qg7","workflow_01.git_04.修改提交信息.md":"D2AhCY_G","web_04.es6_21.arraybuffer.md":"CaXyC-zG","windows_01.windows操作系统查看端口占用.md":"BlE0fRLD","java_02.多线程和高并发_22.juc工具类-semaphore.md":"BBMaPJuY","web_03.javascript_05.常见对象操作_05.boolean对象.md":"6rMBsbuB","windows_02.安装wsl2和子系统.md":"DQC9SpPG","web_03.javascript_05.常见对象操作_06.number对象.md":"BwrrTjpo","web_04.es6_05.数值的扩展.md":"Dhh601kl","web_03.javascript_08.dom操作_05.document节点.md":"Bm4ZlgzL","workflow_01.git_03.github-page部署.md":"B6OUJwv_","web_03.javascript_05.常见对象操作_07.string对象.md":"CRGSlN9K","web_03.javascript_04.语法相关_03.编程风格.md":"B_-kVb0v","web_03.javascript_05.常见对象操作_11.json对象.md":"CJkrHDBD","vue_01.基础_05.监听器.md":"Birrtqu0","vue_01.基础_02.vue常见指令.md":"vyMBzL5w","web_03.javascript_05.常见对象操作_04.包装对象.md":"DDOVmYZ6","web_03.javascript_03.运算符_05.其他运算符及运算顺序.md":"TOcGoFi3","web_03.javascript_08.dom操作_07.属性操作.md":"ce5fcGNa","web_03.javascript_08.dom操作_06.element节点.md":"BPtNUTi_","web_03.javascript_05.常见对象操作_01.object对象.md":"CK_KqDL8","web_03.javascript_08.dom操作_08.text节点.md":"DunQJMMR","web_03.javascript_05.常见对象操作_10.regexp对象.md":"CxkaIXlZ","web_03.javascript_09.杂项_01.鼠标事件区别.md":"C4pjyQXr","web_04.es6_01.let和const.md":"B0HEh_I7","web_03.javascript_08.dom操作_09.css操作.md":"BWUZKan9","web_03.javascript_08.dom操作_10.mutation observer api.md":"2FGwg56X","web_03.javascript_06.面向对象编程_03.对象的继承.md":"niqXFz5c","web_04.es6_02.变量的解构赋值.md":"D-Cekm-h","web_04.es6_03.字符串的扩展以及新增方法.md":"DAwRBqTB","nav.md":"BOdtUJ6p","web_03.javascript_03.运算符_03.布尔运算符.md":"D8H5lSFN","web_04.es6_13.reflect.md":"CyO7sRb_","workflow_01.git_02.git常见命令.md":"DEXZ0eID","web_03.javascript_05.常见对象操作_03.array对象.md":"BoV4Too6","web_03.javascript_01.js基本语法.md":"DaV9DkfV","vue_01.基础_06.vue的生命周期.md":"Bw7ilF6s","linux_02.docker_01.docker安装.md":"DIrDBTWL","web_03.javascript_03.运算符_04.位运算.md":"8ftDfcP3","web_03.javascript_06.面向对象编程_01.实例对象与new命令.md":"Cl4b2m9x","web_04.es6_17. async函数.md":"Cg-X-dXx","web_04.es6_04.正则的扩展.md":"CBc1n09y","linux_02.docker_03.docker安装mysql.md":"z9jd9Q8U","linux_02.docker_04.docker安装redis.md":"DMBU5Fy7","web_03.javascript_04.语法相关_02.错误处理机制.md":"T8b6YLSk","web_03.javascript_02.数据类型_05.对象.md":"id9YjmLn","web_03.javascript_02.数据类型_01.数据类型概述.md":"BHnk8o3c","web_02.css_02.css基础.md":"DJdHjucR","web_03.javascript_07.异步操作_02.promise对象.md":"CLHo0DgD","web_04.es6_20.异步遍历器.md":"Brm6m6lR","java_02.多线程和高并发_06.final关键字.md":"CKb2wKE3","web_03.javascript_08.dom操作_04.parentnode.md":"C_5kELCA","web_04.es6_22.装饰器.md":"BHAYisq2","web_03.javascript_08.dom操作_02.node接口.md":"SDwPOf5s","web_04.es6_14.promise对象.md":"BQ9AADdy","linux_01.corn_01.corn安装及使用.md":"BMdcbmqV","web_03.javascript_03.运算符_02.比较运算符.md":"B0ofbOaD","web_03.javascript_08.dom操作_03.nodelist 接口.md":"BH4sEsjc","java_02.多线程和高并发_08.juc原子类，cas，unsafe.md":"CQx1oaG8","workflow_01.git_05.统计用户提交信息.md":"ULRvsw16","web_03.javascript_02.数据类型_03.数值.md":"DAC-vVsM","web_04.es6_08.对象的扩展及新增方法.md":"ZwrPe_Oj","java_01.java基础_10.集合和泛型.md":"n-y8Cp4U","web_03.javascript_07.异步操作_01.定时器.md":"GdADaSg1","web_04.es6_06.函数的扩展.md":"g0dKmXUu","web_03.javascript_02.数据类型_04.字符串.md":"S7R1nr3g","web_04.es6_18.class基本语法以及继承.md":"BmNmM2bv","web_03.javascript_02.数据类型_06.函数.md":"wd7q63WU","web_03.javascript_06.面向对象编程_02.this关键字.md":"Bj0zyO9c","web_04.es6_15.iterator和for循环.md":"Ct50HWOq","web_04.es6_19.module的语法以及加载实现.md":"DphKfXxG"}
