{"designpatterns_01.设计模式的分类.md":"BU1Z3UKn","designpatterns_02.单例模式.md":"F7L_gTnD","designpatterns_03.原型模式.md":"BV4cqCIR","designpatterns_04.工厂模式.md":"Cw1cI1vG","designpatterns_05.建造者模式.md":"DGUgo9KK","designpatterns_06.代理模式.md":"DhG1qCqZ","designpatterns_07.桥接模式.md":"BSvLOtSI","designpatterns_08.装饰模式.md":"C45ZfE_o","designpatterns_09.外观模式.md":"B51BpYd-","designpatterns_10.享元模式.md":"BOLWK8jZ","designpatterns_11.组合模式.md":"DaYztJCJ","designpatterns_12.模版方法模式.md":"3VWE-GID","designpatterns_13.策略模式.md":"DCKm_8bC","designpatterns_14.命令模式.md":"DMM7S9Pt","designpatterns_15.责任链模式.md":"DUzDiAg2","designpatterns_16.观察者模式.md":"BjJews-b","designpatterns_17.中介者模式.md":"CV9Oywox","designpatterns_18.迭代器模式.md":"B95Hxb4m","designpatterns_19.访问者模式.md":"D9iqO2s0","designpatterns_20.适配器模式.md":"25xWp6QX","designpatterns_21.状态模式.md":"DL8Ko2tx","designpatterns_22.解释器模式.md":"CEycOPd8","designpatterns_23.备忘录模式.md":"BzizRObH","index.md":"D-m68TBy","java_01.java基础_01.基础知识.md":"aCFmffHU","java_01.java基础_02.基础类型.md":"B3SXxEvC","java_01.java基础_03.基本运算符.md":"DI-2aurN","java_01.java基础_04.流程控制语句.md":"CCLZI3J5","java_01.java基础_05.类和对象.md":"D6m8Xc_F","java_01.java基础_06.抽象类.md":"uy3GBrDY","java_01.java基础_06.接口.md":"g5GpvURv","java_01.java基础_07.封装_继承和多态.md":"Cf6eYp_x","java_01.java基础_08.final关键字.md":"evQMZnzg","java_01.java基础_08.修饰符.md":"_lHkhLF0","java_01.java基础_09.包装类.md":"GksLujiX","java_01.java基础_10.集合和泛型.md":"DPwLq5rz","java_01.java基础_11.常见的数据结构.md":"B0eEdb-O","java_01.java基础_12.list接口.md":"BUTt10lp","java_01.java基础_13.set集合.md":"shoMVbpP","java_01.java基础_14.map集合.md":"0RBMur3S","java_01.java基础_15.异常处理机制.md":"Cn0M3qYr","java_01.java基础_16.多线程，线程间通信以及线程池.md":"DD6bw8Rq","java_01.java基础_17.字节流和字符流.md":"DYD91FnY","java_01.java基础_18.缓冲流、转换流、序列化流、打印流.md":"DwEvbOYg","java_01.java基础_19.jvm类加载器.md":"BmMIVBLa","java_01.java基础_20.反射.md":"DT6PzWq5","java_01.java基础_99.8之后的新特新.md":"CSXMaNEm","java_02.多线程和高并发_01.理论基础.md":"ChX9Aiss","java_02.多线程和高并发_02.线程基础.md":"N3DApy3q","java_02.多线程和高并发_03.java中的锁.md":"D0UZWCUM","java_02.多线程和高并发_04.synchronize关键字.md":"B4lWd04F","java_02.多线程和高并发_05.volatile关键字.md":"CJY3p0R3","java_02.多线程和高并发_06.final关键字.md":"Bs3sAi9G","java_02.多线程和高并发_07.juc初解.md":"BTD0iDI2","java_02.多线程和高并发_08.juc原子类，cas，unsafe.md":"CbdiHp1f","java_02.多线程和高并发_09.juc锁-核心类aqs.md":"oDrCd5d5","java_02.多线程和高并发_10.juc锁-locksupport.md":"BdtCSOCt","java_02.多线程和高并发_11.juc锁-reentrantlock详解.md":"BdPpPQV8","java_02.多线程和高并发_12.juc锁-reentrantreadwritelock.md":"CGhGBx-g","java_02.多线程和高并发_13.juc集合-concurrenthashmap.md":"CCj5_c14","java_02.多线程和高并发_14.juc集合-copyonwritearraylist.md":"D_F7pF7f","java_02.多线程和高并发_15.juc集合-concurrentlinkedqueue.md":"CsqtBHq7","java_02.多线程和高并发_16.juc集合-blockingqueue.md":"DwAC6Lty","java_02.多线程和高并发_17.juc线程池-futuretask.md":"opmFxOIu","java_02.多线程和高并发_18.juc线程池-threadpoolexecutor.md":"ZYy7NoWy","java_02.多线程和高并发_19.juc线程池-scheduledthreadpoolexecutor.md":"D0YVtABd","java_02.多线程和高并发_20.juc线程池-forkjoin框架.md":"CAuw0Zti","java_02.多线程和高并发_21.juc工具类-countdownlatch.md":"Cto9yicZ","java_02.多线程和高并发_22.juc工具类-cyclicbarrier.md":"BC65u0Iv","java_02.多线程和高并发_23.juc工具类-semaphore.md":"BbcFkp_O","java_02.多线程和高并发_24.juc工具类-phaser.md":"D_IiY56I","java_02.多线程和高并发_25.juc工具类-exchanger.md":"6OAm7Us6","java_02.多线程和高并发_26.java 并发-threadlocal.md":"ZAB579hG","java_03.jdk集合源码_01.collection类关系图.md":"BRsozeEc","java_03.jdk集合源码_02.hashmap源码解析.md":"eaDZ9Onn","java_03.jdk集合源码_03.arraylist源码解析.md":"BL48iJHr","java_04.jvm_01.jvm相关知识体系详解.md":"Bn6xdMBp","java_05.spring_01.源码编译.md":"DKXYVdKw","java_05.spring_02.源码概览.md":"Cc2rahit","java_05.spring_30.beanfactory和factorybean.md":"BGKV_pN9","linux_01.corn_01.corn安装及使用.md":"JSmUV6kY","linux_02.docker_01.docker安装.md":"DZyhXd3p","linux_02.docker_02.docker命令.md":"DQGHJky8","linux_02.docker_03.docker安装mysql.md":"DZn8Y8BS","linux_02.docker_04.docker安装redis.md":"Dz-mdb_z","linux_02.docker_05.docker安装minio.md":"DRIt58G2","linux_02.docker_06.docker安装nacos.md":"CqX90m2j","linux_02.docker_07.docker安装kafka.md":"CROvTrFk","linux_02.docker_08.docker安装mongodb.md":"CqMJEAQq","linux_02.docker_09.docker安装rocketmq.md":"CLIGBTmx","linux_常见命令.md":"C5zzkGFj","nav.md":"Cfg4Y_Z5","vue_01.基础_01.mvvm模式.md":"tOOVk42n","vue_01.基础_02.vue常见指令.md":"3E04k_Ns","vue_01.基础_03.v-bind增强.md":"1BDD0o03","vue_01.基础_04.v-model在元素中使用.md":"CF-BFsob","vue_01.基础_05.监听器.md":"xjBLjguN","vue_01.基础_06.vue的生命周期.md":"CRtb0yPQ","vue_01.基础_07.脚手架使用及目录介绍.md":"BnX1mKN_","vue_01.基础_08.组件.md":"bQa8ewNx","web_01.html_01.html标签-排序标签.md":"SuA_sE9m","web_01.html_02.html标签-字体标签和超链接.md":"ChaW5StR","web_01.html_03.图片标签.md":"D4HnUbUf","web_02.css_01.css理论知识.md":"CUNCpdsK","web_02.css_02.css基础.md":"Cvv0vRFf","web_03.javascript_01.js基本语法.md":"B_hVhvf5","web_03.javascript_02.数据类型_01.数据类型概述.md":"CMrO0lO5","web_03.javascript_02.数据类型_02.null_ undefined 和布尔值.md":"DaZlerQa","web_03.javascript_02.数据类型_03.数值.md":"D1m6nIoa","web_03.javascript_02.数据类型_04.字符串.md":"CPjcrWFG","web_03.javascript_02.数据类型_05.对象.md":"B7jK9Ffp","web_03.javascript_02.数据类型_06.函数.md":"BFGrw_uC","web_03.javascript_02.数据类型_06.数组.md":"O2gdOh38","web_03.javascript_03.运算符_01.算术运算符.md":"b2KmGydi","web_03.javascript_03.运算符_02.比较运算符.md":"DRIgCtqs","web_03.javascript_03.运算符_03.布尔运算符.md":"KGXu3FAU","web_03.javascript_03.运算符_04.位运算.md":"BCpctPY3","web_03.javascript_03.运算符_05.其他运算符及运算顺序.md":"C9oIDbtO","web_03.javascript_04.语法相关_01.数据类型转化.md":"_Xmv5taJ","web_03.javascript_04.语法相关_02.错误处理机制.md":"wU8VJ-_r","web_03.javascript_04.语法相关_03.编程风格.md":"PX9yGnD5","web_03.javascript_04.语法相关_04.console对象与控制台.md":"D4Cm97zn","web_03.javascript_05.常见对象操作_01.object对象.md":"BAn1wnDL","web_03.javascript_05.常见对象操作_02.属性描述对象.md":"U_c0WO1F","web_03.javascript_05.常见对象操作_03.array对象.md":"DPkkG4zP","web_03.javascript_05.常见对象操作_04.包装对象.md":"BWXgFfev","web_03.javascript_05.常见对象操作_05.boolean对象.md":"nnXpKdhT","web_03.javascript_05.常见对象操作_06.number对象.md":"CdTxf5FY","web_03.javascript_05.常见对象操作_07.string对象.md":"BRLXUEQR","web_03.javascript_05.常见对象操作_08.math对象.md":"D0IkV3-7","web_03.javascript_05.常见对象操作_09.date对象.md":"WzOlcXq3","web_03.javascript_05.常见对象操作_10.regexp对象.md":"Fv1VtPOK","web_03.javascript_05.常见对象操作_11.json对象.md":"ubUGNjIX","web_03.javascript_06.面向对象编程_01.实例对象与new命令.md":"Dcsrq91n","web_03.javascript_06.面向对象编程_02.this关键字.md":"DpYA4Otg","web_03.javascript_06.面向对象编程_03.对象的继承.md":"Do_vppzR","web_03.javascript_06.面向对象编程_04.object对象的相关方法.md":"CO5Qaei7","web_03.javascript_07.异步操作_01.定时器.md":"DY8SbCRb","web_03.javascript_07.异步操作_02.promise对象.md":"CGE42s14","web_03.javascript_08.dom操作_01.概述.md":"BgzVARGJ","web_03.javascript_08.dom操作_02.node接口.md":"BUCBESiL","web_03.javascript_08.dom操作_03.nodelist 接口.md":"B-OA0lAd","web_03.javascript_08.dom操作_04.parentnode.md":"CTxO2y_y","web_03.javascript_08.dom操作_05.document节点.md":"CoR3C35c","web_03.javascript_08.dom操作_06.element节点.md":"DEGwlRor","web_03.javascript_08.dom操作_07.属性操作.md":"vczzhE7o","web_03.javascript_08.dom操作_08.text节点.md":"wJzGse_t","web_03.javascript_08.dom操作_09.css操作.md":"ZG1DcaRJ","web_03.javascript_08.dom操作_10.mutation observer api.md":"DRH-jJfX","web_03.javascript_09.杂项_01.鼠标事件区别.md":"CZcaZ5ag","web_04.es6_01.let和const.md":"DK-gMY-8","web_04.es6_02.变量的解构赋值.md":"DctjDrM6","web_04.es6_03.字符串的扩展以及新增方法.md":"BHLoWGvX","web_04.es6_04.正则的扩展.md":"COjlfpg6","web_04.es6_05.数值的扩展.md":"C0Xdx-XL","web_04.es6_06.函数的扩展.md":"_ZllJ1cF","web_04.es6_07.数组的扩展.md":"DKs7zP8S","web_04.es6_08.对象的扩展及新增方法.md":"CwHgjLjP","web_04.es6_09.运算符的扩展.md":"Cal7y631","web_04.es6_10.symbol.md":"C7a1JxI8","web_04.es6_11.set和map.md":"Ci1ZnXpp","web_04.es6_12.proxy.md":"BIbE_VgL","web_04.es6_13.reflect.md":"D98A_HLx","web_04.es6_14.promise对象.md":"ClX1PxEg","web_04.es6_15.iterator和for循环.md":"D1qGvxj5","web_04.es6_16. generator函数以及异步应用.md":"CI0yYPHg","web_04.es6_17. async函数.md":"D7CgrQ2S","web_04.es6_18.class基本语法以及继承.md":"mtz4pbGS","web_04.es6_19.module的语法以及加载实现.md":"B_Fs9Mfu","web_04.es6_20.异步遍历器.md":"DunqnD6T","web_04.es6_21.arraybuffer.md":"VnWDtj7z","web_04.es6_22.装饰器.md":"DUwRvvWo","windows_01.windows操作系统查看端口占用.md":"BpEqpHzW","windows_02.安装wsl2和子系统.md":"CoZySA7G","workflow_01.git_01.git基本操作.md":"ZfMyUdXn","workflow_01.git_02.git常见命令.md":"DtvM3e_I","workflow_01.git_03.github-page部署.md":"-wCw5bSQ","workflow_01.git_04.修改提交信息.md":"CzK7fVIo","workflow_01.git_05.统计用户提交信息.md":"gtcdZToo"}
